fineract/__init__.py
PyFineract-0.0.3.dist-info/LICENSE
PyFineract-0.0.3.dist-info/METADATA
PyFineract-0.0.3.dist-info/WHEEL
PyFineract-0.0.3.dist-info/top_level.txt
PyFineract-0.0.3.dist-info/RECORD
